journal_rss/__init__.py
journal_rss/__main__.py
journal_rss/app.py
journal_rss/config.py
journal_rss/const.py
journal_rss/db.py
journal_rss/decorators.py
journal_rss/logging.py
journal_rss/main.py
journal_rss/models/__init__.py
journal_rss/models/api.py
journal_rss/models/journal.py
journal_rss/models/paper.py
journal_rss/models/rss.py
journal_rss/services/__init__.py
journal_rss/services/crossref.py
journal_rss/services/db.py
journal_rss/services/rss.py
journal_rss-0.0.1.dist-info/LICENSE
journal_rss-0.0.1.dist-info/METADATA
journal_rss-0.0.1.dist-info/WHEEL
journal_rss-0.0.1.dist-info/entry_points.txt
journal_rss-0.0.1.dist-info/RECORD
